tree2cmd/__init__.py
tree2cmd/cli.py
tree2cmd/parser.py
tree2cmd/utils.py
tree2cmd-0.4.4.dist-info/licenses/LICENSE
tree2cmd-0.4.4.dist-info/METADATA
tree2cmd-0.4.4.dist-info/WHEEL
tree2cmd-0.4.4.dist-info/entry_points.txt
tree2cmd-0.4.4.dist-info/top_level.txt
tree2cmd-0.4.4.dist-info/RECORD
