Metadata-Version: 2.4
Name: tree2cmd
Version: 0.4.4
Summary: Convert text directory trees (struct.txt) into real folders and files.
Home-page: https://github.com/ajmanjoma/tree2cmd
Author: Antony Joseph Mathew
Author-email: Antony Joseph Mathew <antonyjosephmathew1@gmail.com>
License: MIT License
Project-URL: Homepage, https://github.com/ajmanjoma/tree2cmd
Project-URL: Repository, https://github.com/ajmanjoma/tree2cmd
Project-URL: Issues, https://github.com/ajmanjoma/tree2cmd/issues
Project-URL: Documentation, https://github.com/ajmanjoma/tree2cmd/tree/main/docs
Keywords: tree,folder generator,project scaffolding,cli,filesystem,structure parser,automation
Classifier: Programming Language :: Python
Classifier: Programming Language :: Python :: 3
Classifier: Programming Language :: Python :: 3.8
Classifier: Programming Language :: Python :: 3.9
Classifier: Programming Language :: Python :: 3.10
Classifier: Programming Language :: Python :: 3.11
Classifier: Programming Language :: Python :: 3.12
Classifier: License :: OSI Approved :: MIT License
Classifier: Operating System :: OS Independent
Classifier: Environment :: Console
Classifier: Topic :: Utilities
Classifier: Topic :: Software Development :: Code Generators
Requires-Python: >=3.8
License-File: LICENSE
Provides-Extra: dev
Requires-Dist: black; extra == "dev"
Requires-Dist: flake8; extra == "dev"
Requires-Dist: mypy; extra == "dev"
Requires-Dist: build; extra == "dev"
Requires-Dist: twine; extra == "dev"
Requires-Dist: bump2version; extra == "dev"
Dynamic: author
Dynamic: home-page
Dynamic: license-file
Dynamic: requires-python
